pycfm/__init__.py
pycfm/complemento.py
pycfm/main.py
pycfm/others.py
pycfm-0.4.3.dist-info/licenses/LICENSE
pycfm-0.4.3.dist-info/METADATA
pycfm-0.4.3.dist-info/WHEEL
pycfm-0.4.3.dist-info/top_level.txt
pycfm-0.4.3.dist-info/RECORD
