Metadata-Version: 2.4
Name: pycfm
Version: 0.4.3
Summary: Obtem dados de médicos acessando informações do Conselho Federal de Medicina
Author-email: michelmetran <michelmetran@gmail.com>
Project-URL: Issues, https://github.com/michelmetran/pyCFM/issues/
Project-URL: Documentation, https://pycfm.readthedocs.io/pt/latest/
Project-URL: Repository, https://github.com/michelmetran/pyCFM/
Project-URL: Discussions, https://github.com/michelmetran/pyCFM/discussions
Keywords: CRM,CFM,github,médicos
Requires-Python: >=3.11
License-File: LICENSE
Requires-Dist: pandas>=2.2.2
Requires-Dist: requests>=2.32.0
Requires-Dist: tabulate>=0.9.0
Dynamic: license-file
